{
	"institutions":[
		{
			"date": "2022 -2023",
			"school": "ISEN Yncréa Ouest",
			"info": "Courses and practical works in Microsoft Excel",
			"Hours": "15",
			"link": "https://isen-nantes.fr/",
			"department": "Nantes Campus"
		},
		{
			"date": "2022 -2023",
			"school": "ISEN Yncréa Ouest",
			"info": "Practical work and supervision of projects in Python",
			"Hours": "38",
			"link": "https://isen-nantes.fr/",
			"department": "Nantes Campus"
		}

	]
}






